{"errors":[],"warnings":[],"namedChunkGroups":{"polyfill":{"chunks":[0,5],"assets":["webpack-runtime-ce04e497f3b17cb28445.js","webpack-runtime-ce04e497f3b17cb28445.js.map","polyfill-26549e177e9ca9be87da.js","polyfill-26549e177e9ca9be87da.js.map"],"children":{},"childAssets":{}},"app":{"chunks":[0,4,2],"assets":["webpack-runtime-ce04e497f3b17cb28445.js","webpack-runtime-ce04e497f3b17cb28445.js.map","framework-06f646d936b841f99ebd.js","framework-06f646d936b841f99ebd.js.map","app-0a35a001b545078f5559.js","app-0a35a001b545078f5559.js.map"],"children":{},"childAssets":{}},"component---src-deck-mdx":{"chunks":[1,3],"assets":["1f855128-fe613a5224842876f542.js","1f855128-fe613a5224842876f542.js.map","component---src-deck-mdx-0e49985ca06dce43267d.js","component---src-deck-mdx-0e49985ca06dce43267d.js.map"],"children":{},"childAssets":{}}},"assetsByChunkName":{"polyfill":["webpack-runtime-ce04e497f3b17cb28445.js","polyfill-26549e177e9ca9be87da.js"],"app":["webpack-runtime-ce04e497f3b17cb28445.js","framework-06f646d936b841f99ebd.js","app-0a35a001b545078f5559.js"],"component---src-deck-mdx":["1f855128-fe613a5224842876f542.js","component---src-deck-mdx-0e49985ca06dce43267d.js"]}}